Metadata-Version: 2.1
Name: odoo12-addon-l10n_es_aeat_sii_extra_data
Version: 12.0.1.0.0.99.dev5
Summary: Módulo para incluir los impuestos extra en el módulo del SII.
Home-page: https://github.com/OCA/l10n-spain
Author: Trey (www.trey.es), Odoo Community Association (OCA)
Author-email: support@odoo-community.org
License: AGPL-3
Classifier: Programming Language :: Python
Classifier: Framework :: Odoo
Classifier: Framework :: Odoo :: 12.0
Classifier: License :: OSI Approved :: GNU Affero General Public License v3
Requires-Python: >=3.5
Requires-Dist: odoo12-addon-l10n-es-aeat-sii
Requires-Dist: odoo12-addon-l10n-es-extra-data
Requires-Dist: odoo<12.1dev,>=12.0a
